popsom7/__init__.py
popsom7/maputils.py
popsom7/sklearnapi.py
popsom7-7.1.2.dist-info/licenses/LICENSE
popsom7-7.1.2.dist-info/METADATA
popsom7-7.1.2.dist-info/WHEEL
popsom7-7.1.2.dist-info/top_level.txt
popsom7-7.1.2.dist-info/RECORD
