Metadata-Version: 2.4
Name: popsom7
Version: 7.1.2
Summary: A Fast, User-friendly Implementation of Self-Organizing Maps (SOMs)
Home-page: https://github.com/lutzhamel/popsom7
Author: Lutz Hamel
Author-email: lutz.hamel@gmail.com
Classifier: Programming Language :: Python :: 3
Classifier: License :: OSI Approved :: GNU General Public License v3 (GPLv3)
Classifier: Operating System :: OS Independent
Requires-Python: >=3.6
License-File: LICENSE
Requires-Dist: numpy
Requires-Dist: pandas
Requires-Dist: seaborn
Requires-Dist: matplotlib
Requires-Dist: scipy
Dynamic: author
Dynamic: author-email
Dynamic: classifier
Dynamic: description
Dynamic: description-content-type
Dynamic: home-page
Dynamic: license-file
Dynamic: requires-dist
Dynamic: requires-python
Dynamic: summary
